{
  "kind": "collectionType",
  "collectionName": "galleries",
  "info": {
    "singularName": "gallery",
    "pluralName": "galleries",
    "displayName": "gallery",
    "description": ""
  },
  "options": {
    "draftAndPublish": true
  },
  "pluginOptions": {},
  "attributes": {
    "label": {
      "type": "string"
    },
    "images": {
      "type": "component",
      "repeatable": true,
      "component": "gallery.gallery-image"
    },
    "description": {
      "type": "richtext",
      "maxLength": 350
    }
  }
}
